[
  {
    "name": "TodoList",
    "image": "./assets/pomodoro.png",
    "tags": ["JavaScript", "React", "SCSS", "HTML, Redux"],
    "link": "https://todo-list-delta-drab.vercel.app/"
  },
  {
    "name": "TestFrontEnd-Kbrtec",
    "image": "./assets/kbrtec.png",
    "tags": ["JavaScript", "React", "SCSS", "HTML", "Gulp", "Responsive"],
    "link": "https://kbrtec-teste-dusky.vercel.app/"
  },
  {
    "name": "TestFrontEnd",
    "image": "./assets/Vtex.png",
    "tags": ["TypeScript", "React", "SCSS", "HTML"],
    "link": "https://teste-front-end-jr-7pnb.vercel.app/"
  },
	{
    "name": "PokeAPI",
    "image": "./assets/pokemonLogo.png",
    "tags": ["JavaScript", "React", "HTML", "CSS"],
    "link": "https://pokedex-xi-red.vercel.app/"
  },
	{
    "name": "IronGym",
    "image": "./assets/bgTestimonials.png",
    "tags": ["JavaScript", "React", "Conteudo &copy;IronGyn", "SCSS", "HTML"],
    "link": "https://iron-gym-pearl.vercel.app/"
  },
  {
    "name": "Sistema de Login",
    "image": "./assets/Login.png",
    "tags": ["HTML", "React", "CSS"],
    "link": "https://login-estudando.vercel.app/"
  }
]